twmn_mpd/MPDState.py
twmn_mpd/MsgQueue.py
twmn_mpd/NotificationProvider.py
twmn_mpd/TWMNSocketClient.py
twmn_mpd/__init__.py
twmn_mpd/utils.py
twmn_mpd/providers/NowPlayingNotifier.py
twmn_mpd/providers/PlayStateNotifier.py
twmn_mpd/providers/__init__.py
twmn_mpd-0.1.6.dist-info/DESCRIPTION.rst
twmn_mpd-0.1.6.dist-info/METADATA
twmn_mpd-0.1.6.dist-info/RECORD
twmn_mpd-0.1.6.dist-info/WHEEL
twmn_mpd-0.1.6.dist-info/entry_points.txt
twmn_mpd-0.1.6.dist-info/metadata.json
twmn_mpd-0.1.6.dist-info/top_level.txt
