Metadata-Version: 2.0
Name: twmn-mpd
Version: 0.1.6
Summary: A simple mpd notifier for twmn
Home-page: http://github.com/mrkgnao/twmn-mpd
Author: Soham Chowdhury
Author-email: chow.soham@gmail.com
License: MIT
Platform: UNKNOWN
Requires-Dist: python-mpd2
